{"cameraMode":{"drawMode":0,"name":"Shaded","section":"Shading Mode"},"sceneLighting":true,"audioPlay":false,"sceneViewState":{"m_AlwaysRefresh":false,"showFog":true,"showSkybox":true,"showFlares":true,"showImageEffects":true,"showParticleSystems":true,"showVisualEffectGraphs":true,"m_FxEnabled":true},"in2DMode":false,"pivot":{"x":-3.062692642211914,"y":3.872939109802246,"z":-2.0285987854003908},"rotation":{"x":0.025232242420315744,"y":0.777450680732727,"z":0.03126663342118263,"w":-0.6276660561561585},"size":6.09547758102417,"orthographic":false}