{"cameraMode":{"drawMode":0,"name":"Shaded","section":"Shading Mode"},"sceneLighting":true,"audioPlay":false,"sceneViewState":{"m_AlwaysRefresh":false,"showFog":true,"showSkybox":true,"showFlares":true,"showImageEffects":true,"showParticleSystems":true,"showVisualEffectGraphs":true,"m_FxEnabled":true},"in2DMode":false,"pivot":{"x":0.0,"y":6.0,"z":-5.0},"rotation":{"x":-0.15498225390911103,"y":0.5478839874267578,"z":-0.1041208952665329,"w":-0.8154575824737549},"size":12.12435531616211,"orthographic":false}